{
	"credit": "Made By SamXU1322",
	"textures": {
		"particle": "block/bamboo_stalk",
		"all": "block/bamboo_stalk"
	},
	"elements": [
		{
			"from": [6, 0, 6],
			"to": [10, 16, 10],
			"faces": {
				"north": {"uv": [6, 0, 10, 16], "texture": "#all"},
				"east": {"uv": [6, 0, 10, 16], "texture": "#all"},
				"south": {"uv": [6, 0, 10, 16], "texture": "#all"},
				"west": {"uv": [6, 0, 10, 16], "texture": "#all"},
				"up": {"uv": [12, 0, 16, 4], "texture": "#all", "cullface": "up"},
				"down": {"uv": [12, 4, 16, 8], "texture": "#all", "cullface": "down"}
			}
		}
	]
}